audio_player/__init__.py
audio_player/player.py
audio_player_lib-0.1.0.dist-info/licenses/LICENSE
audio_player_lib-0.1.0.dist-info/METADATA
audio_player_lib-0.1.0.dist-info/WHEEL
audio_player_lib-0.1.0.dist-info/top_level.txt
audio_player_lib-0.1.0.dist-info/RECORD
