Metadata-Version: 2.4
Name: audio_player_lib
Version: 0.1.0
License-File: LICENSE
Requires-Dist: pydub
Dynamic: license-file
Dynamic: requires-dist
